{
  "appInfo" : {
    "build" : "252.12832",
    "buildDate" : "2025-04-30T10:39:00Z[UTC]",
    "productCode" : "FLIJ",
    "generated" : "2025-05-13T06:40:12.63528971Z",
    "os" : "Linux 6.14.0-0.rc3.29.fc42.x86_64",
    "runtime" : "JetBrains s.r.o. 21.0.6 21.0.6+9-b929.24"
  },
  "runtimeInfo" : {
    "maxMemory" : 891289600,
    "numberOfProcessors" : 12,
    "maxNumberOfIndexingThreads" : 12,
    "maxSizeOfFileForIntelliSense" : 2560000,
    "maxSizeOfFileForContentLoading" : 20971520
  },
  "type" : "Scanning",
  "projectIndexingActivityHistory" : {
    "projectName" : "nestjs-demo",
    "times" : {
      "scanningReason" : "On project open",
      "scanningType" : "FULL_ON_PROJECT_OPEN",
      "scanningId" : 0,
      "creatingIteratorsTime" : 0,
      "concurrentHandlingWallTimeWithoutPauses" : 0,
      "concurrentHandlingWallTimeWithPauses" : 0,
      "concurrentHandlingSumOfThreadTimesWithPauses" : 6640668106,
      "concurrentIterationAndScannersApplicationSumOfThreadTimesWithPauses" : 680044313,
      "concurrentFileCheckSumOfThreadTimesWithPauses" : 5924061104,
      "delayedPushPropertiesStageTime" : 0,
      "indexExtensionsTime" : 55110005,
      "dumbModeStart" : "2025-05-13T06:40:12.156558814Z",
      "dumbWallTimeWithPauses" : 470073122,
      "dumbWallTimeWithoutPauses" : 470073122,
      "updatingStart" : "2025-05-13T06:40:10.955804011Z",
      "updatingEnd" : "2025-05-13T06:40:12.626631936Z",
      "totalWallTimeWithPauses" : 1670827925,
      "wallTimeOnPause" : 1715224,
      "isCancelled" : true,
      "cancellationReason" : "java.util.concurrent.CancellationException: Full scanning is queued",
      "totalWallTimeWithoutPauses" : 1669112701
    },
    "fileCount" : {
      "numberOfFileProviders" : 23,
      "numberOfScannedFiles" : 736,
      "numberOfFilesIndexedByInfrastructureExtensionsDuringScan" : 0,
      "numberOfFilesScheduledForIndexingAfterScan" : 736
    },
    "scanningStatistics" : [ {
      "providerName" : "External roots from entity (geoip, odbc, recode, ...; empty; empty; empty)",
      "numberOfScannedFiles" : 269,
      "numberOfSkippedFiles" : 0,
      "numberOfFilesForIndexing" : 269,
      "numberOfFilesFullyIndexedByInfrastructureExtensions" : 0,
      "filesFullyIndexedByInfrastructureExtensions" : [ ],
      "statusTime" : 266331031,
      "totalOneThreadTimeWithPauses" : 1013135980,
      "iterationAndScannersApplicationTime" : 408210690,
      "filesCheckTime" : 602784492,
      "timeProcessingUpToDateFiles" : 0,
      "timeUpdatingContentLessIndexes" : 103435105,
      "timeIndexingWithoutContentViaInfrastructureExtension" : 35305013,
      "roots" : [ ]
    }, {
      "providerName" : "Indexable set contributor 'com.intellij.javaee.ExternalResourcesRootsProvider@7a427767' (non-project)",
      "numberOfScannedFiles" : 320,
      "numberOfSkippedFiles" : 4,
      "numberOfFilesForIndexing" : 320,
      "numberOfFilesFullyIndexedByInfrastructureExtensions" : 0,
      "filesFullyIndexedByInfrastructureExtensions" : [ ],
      "statusTime" : 269527401,
      "totalOneThreadTimeWithPauses" : 992069091,
      "iterationAndScannersApplicationTime" : 119406545,
      "filesCheckTime" : 870194166,
      "timeProcessingUpToDateFiles" : 0,
      "timeUpdatingContentLessIndexes" : 124476142,
      "timeIndexingWithoutContentViaInfrastructureExtension" : 11402200,
      "roots" : [ ]
    }, {
      "providerName" : "Indexable set contributor 'JS required libraries' (project)",
      "numberOfScannedFiles" : 97,
      "numberOfSkippedFiles" : 0,
      "numberOfFilesForIndexing" : 97,
      "numberOfFilesFullyIndexedByInfrastructureExtensions" : 0,
      "filesFullyIndexedByInfrastructureExtensions" : [ ],
      "statusTime" : 151503574,
      "totalOneThreadTimeWithPauses" : 715352404,
      "iterationAndScannersApplicationTime" : 7357854,
      "filesCheckTime" : 704734266,
      "timeProcessingUpToDateFiles" : 0,
      "timeUpdatingContentLessIndexes" : 44406961,
      "timeIndexingWithoutContentViaInfrastructureExtension" : 3588802,
      "roots" : [ ]
    }, {
      "providerName" : "Module 'nestjs-demo-fleet' (all roots)",
      "numberOfScannedFiles" : 16,
      "numberOfSkippedFiles" : 0,
      "numberOfFilesForIndexing" : 16,
      "numberOfFilesFullyIndexedByInfrastructureExtensions" : 0,
      "filesFullyIndexedByInfrastructureExtensions" : [ ],
      "statusTime" : 48582727,
      "totalOneThreadTimeWithPauses" : 644123437,
      "iterationAndScannersApplicationTime" : 56614578,
      "filesCheckTime" : 579370898,
      "timeProcessingUpToDateFiles" : 0,
      "timeUpdatingContentLessIndexes" : 8365763,
      "timeIndexingWithoutContentViaInfrastructureExtension" : 918548,
      "roots" : [ ]
    }, {
      "providerName" : "Custom kind roots from entity (sass_functions.scss, sass_color.scss, sass_list.scss, ..., empty)",
      "numberOfScannedFiles" : 8,
      "numberOfSkippedFiles" : 0,
      "numberOfFilesForIndexing" : 8,
      "numberOfFilesFullyIndexedByInfrastructureExtensions" : 0,
      "filesFullyIndexedByInfrastructureExtensions" : [ ],
      "statusTime" : 30309618,
      "totalOneThreadTimeWithPauses" : 550997369,
      "iterationAndScannersApplicationTime" : 6058117,
      "filesCheckTime" : 539923346,
      "timeProcessingUpToDateFiles" : 0,
      "timeUpdatingContentLessIndexes" : 11541136,
      "timeIndexingWithoutContentViaInfrastructureExtension" : 558875,
      "roots" : [ ]
    }, {
      "providerName" : "Indexable set contributor 'TypeScript bundled libraries' (project)",
      "numberOfScannedFiles" : 16,
      "numberOfSkippedFiles" : 75,
      "numberOfFilesForIndexing" : 16,
      "numberOfFilesFullyIndexedByInfrastructureExtensions" : 0,
      "filesFullyIndexedByInfrastructureExtensions" : [ ],
      "statusTime" : 47378699,
      "totalOneThreadTimeWithPauses" : 457392580,
      "iterationAndScannersApplicationTime" : 15497705,
      "filesCheckTime" : 441855404,
      "timeProcessingUpToDateFiles" : 0,
      "timeUpdatingContentLessIndexes" : 12917894,
      "timeIndexingWithoutContentViaInfrastructureExtension" : 1132998,
      "roots" : [ ]
    }, {
      "providerName" : "Indexable set contributor 'org.jetbrains.kotlin.idea.base.indices.contributors.BuiltInsIndexableSetContributor@5b699ba5' (non-project)",
      "numberOfScannedFiles" : 8,
      "numberOfSkippedFiles" : 0,
      "numberOfFilesForIndexing" : 8,
      "numberOfFilesFullyIndexedByInfrastructureExtensions" : 0,
      "filesFullyIndexedByInfrastructureExtensions" : [ ],
      "statusTime" : 32445818,
      "totalOneThreadTimeWithPauses" : 443780142,
      "iterationAndScannersApplicationTime" : 9051971,
      "filesCheckTime" : 434654510,
      "timeProcessingUpToDateFiles" : 0,
      "timeUpdatingContentLessIndexes" : 16407735,
      "timeIndexingWithoutContentViaInfrastructureExtension" : 2043879,
      "roots" : [ ]
    }, {
      "providerName" : "Indexable set contributor 'com.intellij.httpClient.http.request.HttpRequestCollectionProvider@61d58141' (non-project)",
      "numberOfScannedFiles" : 2,
      "numberOfSkippedFiles" : 0,
      "numberOfFilesForIndexing" : 2,
      "numberOfFilesFullyIndexedByInfrastructureExtensions" : 0,
      "filesFullyIndexedByInfrastructureExtensions" : [ ],
      "statusTime" : 25328792,
      "totalOneThreadTimeWithPauses" : 397172512,
      "iterationAndScannersApplicationTime" : 12243238,
      "filesCheckTime" : 384868676,
      "timeProcessingUpToDateFiles" : 0,
      "timeUpdatingContentLessIndexes" : 11545909,
      "timeIndexingWithoutContentViaInfrastructureExtension" : 159690,
      "roots" : [ ]
    }, {
      "providerName" : "Indexable set contributor 'JS required libraries' (non-project)",
      "numberOfScannedFiles" : 0,
      "numberOfSkippedFiles" : 12,
      "numberOfFilesForIndexing" : 0,
      "numberOfFilesFullyIndexedByInfrastructureExtensions" : 0,
      "filesFullyIndexedByInfrastructureExtensions" : [ ],
      "statusTime" : 0,
      "totalOneThreadTimeWithPauses" : 373331488,
      "iterationAndScannersApplicationTime" : 13393179,
      "filesCheckTime" : 359869863,
      "timeProcessingUpToDateFiles" : 0,
      "timeUpdatingContentLessIndexes" : 0,
      "timeIndexingWithoutContentViaInfrastructureExtension" : 0,
      "roots" : [ ]
    }, {
      "providerName" : "Indexable set contributor 'fleet.backend.codeinsight.FleetImaginaryFileIndexableSetContributor@51084223' (non-project)",
      "numberOfScannedFiles" : 0,
      "numberOfSkippedFiles" : 0,
      "numberOfFilesForIndexing" : 0,
      "numberOfFilesFullyIndexedByInfrastructureExtensions" : 0,
      "filesFullyIndexedByInfrastructureExtensions" : [ ],
      "statusTime" : 0,
      "totalOneThreadTimeWithPauses" : 174948554,
      "iterationAndScannersApplicationTime" : 11067652,
      "filesCheckTime" : 162115544,
      "timeProcessingUpToDateFiles" : 0,
      "timeUpdatingContentLessIndexes" : 0,
      "timeIndexingWithoutContentViaInfrastructureExtension" : 0,
      "roots" : [ ]
    }, {
      "providerName" : "Indexable set contributor 'Scratches & Consoles' (non-project)",
      "numberOfScannedFiles" : 0,
      "numberOfSkippedFiles" : 0,
      "numberOfFilesForIndexing" : 0,
      "numberOfFilesFullyIndexedByInfrastructureExtensions" : 0,
      "filesFullyIndexedByInfrastructureExtensions" : [ ],
      "statusTime" : 0,
      "totalOneThreadTimeWithPauses" : 144882250,
      "iterationAndScannersApplicationTime" : 3219165,
      "filesCheckTime" : 139602523,
      "timeProcessingUpToDateFiles" : 0,
      "timeUpdatingContentLessIndexes" : 0,
      "timeIndexingWithoutContentViaInfrastructureExtension" : 0,
      "roots" : [ ]
    }, {
      "providerName" : "Indexable set contributor 'org.jetbrains.plugins.scss.index.SassScssIndexedRootProvider@6be6f121' (non-project)",
      "numberOfScannedFiles" : 0,
      "numberOfSkippedFiles" : 0,
      "numberOfFilesForIndexing" : 0,
      "numberOfFilesFullyIndexedByInfrastructureExtensions" : 0,
      "filesFullyIndexedByInfrastructureExtensions" : [ ],
      "statusTime" : 0,
      "totalOneThreadTimeWithPauses" : 144699952,
      "iterationAndScannersApplicationTime" : 3526624,
      "filesCheckTime" : 138941394,
      "timeProcessingUpToDateFiles" : 0,
      "timeUpdatingContentLessIndexes" : 0,
      "timeIndexingWithoutContentViaInfrastructureExtension" : 0,
      "roots" : [ ]
    }, {
      "providerName" : "Indexable set contributor 'Scratches & Consoles' (project)",
      "numberOfScannedFiles" : 0,
      "numberOfSkippedFiles" : 0,
      "numberOfFilesForIndexing" : 0,
      "numberOfFilesFullyIndexedByInfrastructureExtensions" : 0,
      "filesFullyIndexedByInfrastructureExtensions" : [ ],
      "statusTime" : 0,
      "totalOneThreadTimeWithPauses" : 144684683,
      "iterationAndScannersApplicationTime" : 3721013,
      "filesCheckTime" : 138693870,
      "timeProcessingUpToDateFiles" : 0,
      "timeUpdatingContentLessIndexes" : 0,
      "timeIndexingWithoutContentViaInfrastructureExtension" : 0,
      "roots" : [ ]
    }, {
      "providerName" : "Indexable set contributor 'fleet.backend.codeinsight.FleetImaginaryFileIndexableSetContributor@51084223' (project)",
      "numberOfScannedFiles" : 0,
      "numberOfSkippedFiles" : 0,
      "numberOfFilesForIndexing" : 0,
      "numberOfFilesFullyIndexedByInfrastructureExtensions" : 0,
      "filesFullyIndexedByInfrastructureExtensions" : [ ],
      "statusTime" : 0,
      "totalOneThreadTimeWithPauses" : 144630271,
      "iterationAndScannersApplicationTime" : 3046276,
      "filesCheckTime" : 139036645,
      "timeProcessingUpToDateFiles" : 0,
      "timeUpdatingContentLessIndexes" : 0,
      "timeIndexingWithoutContentViaInfrastructureExtension" : 0,
      "roots" : [ ]
    }, {
      "providerName" : "Indexable set contributor 'com.intellij.javaee.ExternalResourcesRootsProvider@7a427767' (project)",
      "numberOfScannedFiles" : 0,
      "numberOfSkippedFiles" : 0,
      "numberOfFilesForIndexing" : 0,
      "numberOfFilesFullyIndexedByInfrastructureExtensions" : 0,
      "filesFullyIndexedByInfrastructureExtensions" : [ ],
      "statusTime" : 0,
      "totalOneThreadTimeWithPauses" : 144613386,
      "iterationAndScannersApplicationTime" : 3259524,
      "filesCheckTime" : 138975645,
      "timeProcessingUpToDateFiles" : 0,
      "timeUpdatingContentLessIndexes" : 0,
      "timeIndexingWithoutContentViaInfrastructureExtension" : 0,
      "roots" : [ ]
    }, {
      "providerName" : "Indexable set contributor 'org.jetbrains.plugins.scss.index.SassScssIndexedRootProvider@6be6f121' (project)",
      "numberOfScannedFiles" : 0,
      "numberOfSkippedFiles" : 0,
      "numberOfFilesForIndexing" : 0,
      "numberOfFilesFullyIndexedByInfrastructureExtensions" : 0,
      "filesFullyIndexedByInfrastructureExtensions" : [ ],
      "statusTime" : 0,
      "totalOneThreadTimeWithPauses" : 144329663,
      "iterationAndScannersApplicationTime" : 4059525,
      "filesCheckTime" : 138550504,
      "timeProcessingUpToDateFiles" : 0,
      "timeUpdatingContentLessIndexes" : 0,
      "timeIndexingWithoutContentViaInfrastructureExtension" : 0,
      "roots" : [ ]
    }, {
      "providerName" : "Indexable set contributor 'TypeScript bundled libraries' (non-project)",
      "numberOfScannedFiles" : 0,
      "numberOfSkippedFiles" : 0,
      "numberOfFilesForIndexing" : 0,
      "numberOfFilesFullyIndexedByInfrastructureExtensions" : 0,
      "filesFullyIndexedByInfrastructureExtensions" : [ ],
      "statusTime" : 0,
      "totalOneThreadTimeWithPauses" : 1867704,
      "iterationAndScannersApplicationTime" : 205613,
      "filesCheckTime" : 1632683,
      "timeProcessingUpToDateFiles" : 0,
      "timeUpdatingContentLessIndexes" : 0,
      "timeIndexingWithoutContentViaInfrastructureExtension" : 0,
      "roots" : [ ]
    }, {
      "providerName" : "Indexable set contributor 'org.jetbrains.kotlin.idea.base.indices.contributors.BuiltInsIndexableSetContributor@5b699ba5' (project)",
      "numberOfScannedFiles" : 0,
      "numberOfSkippedFiles" : 0,
      "numberOfFilesForIndexing" : 0,
      "numberOfFilesFullyIndexedByInfrastructureExtensions" : 0,
      "filesFullyIndexedByInfrastructureExtensions" : [ ],
      "statusTime" : 0,
      "totalOneThreadTimeWithPauses" : 1622346,
      "iterationAndScannersApplicationTime" : 11878,
      "filesCheckTime" : 1585992,
      "timeProcessingUpToDateFiles" : 0,
      "timeUpdatingContentLessIndexes" : 0,
      "timeIndexingWithoutContentViaInfrastructureExtension" : 0,
      "roots" : [ ]
    }, {
      "providerName" : "Indexable set contributor 'com.jetbrains.php.config.library.PhpRuntimeLibraryRootsProvider@5aa99b01' (project)",
      "numberOfScannedFiles" : 0,
      "numberOfSkippedFiles" : 0,
      "numberOfFilesForIndexing" : 0,
      "numberOfFilesFullyIndexedByInfrastructureExtensions" : 0,
      "filesFullyIndexedByInfrastructureExtensions" : [ ],
      "statusTime" : 0,
      "totalOneThreadTimeWithPauses" : 1459038,
      "iterationAndScannersApplicationTime" : 34052,
      "filesCheckTime" : 1357721,
      "timeProcessingUpToDateFiles" : 0,
      "timeUpdatingContentLessIndexes" : 0,
      "timeIndexingWithoutContentViaInfrastructureExtension" : 0,
      "roots" : [ ]
    }, {
      "providerName" : "Indexable set contributor 'com.intellij.httpClient.http.request.HttpRequestCollectionProvider@61d58141' (project)",
      "numberOfScannedFiles" : 0,
      "numberOfSkippedFiles" : 0,
      "numberOfFilesForIndexing" : 0,
      "numberOfFilesFullyIndexedByInfrastructureExtensions" : 0,
      "filesFullyIndexedByInfrastructureExtensions" : [ ],
      "statusTime" : 0,
      "totalOneThreadTimeWithPauses" : 1422566,
      "iterationAndScannersApplicationTime" : 9752,
      "filesCheckTime" : 1374183,
      "timeProcessingUpToDateFiles" : 0,
      "timeUpdatingContentLessIndexes" : 0,
      "timeIndexingWithoutContentViaInfrastructureExtension" : 0,
      "roots" : [ ]
    }, {
      "providerName" : "Indexable set contributor 'com.jetbrains.php.config.library.PhpRuntimeLibraryRootsProvider@5aa99b01' (non-project)",
      "numberOfScannedFiles" : 0,
      "numberOfSkippedFiles" : 0,
      "numberOfFilesForIndexing" : 0,
      "numberOfFilesFullyIndexedByInfrastructureExtensions" : 0,
      "filesFullyIndexedByInfrastructureExtensions" : [ ],
      "statusTime" : 0,
      "totalOneThreadTimeWithPauses" : 1407727,
      "iterationAndScannersApplicationTime" : 14648,
      "filesCheckTime" : 1316791,
      "timeProcessingUpToDateFiles" : 0,
      "timeUpdatingContentLessIndexes" : 0,
      "timeIndexingWithoutContentViaInfrastructureExtension" : 0,
      "roots" : [ ]
    }, {
      "providerName" : "Indexable set contributor 'Version Catalogs' (project)",
      "numberOfScannedFiles" : 0,
      "numberOfSkippedFiles" : 0,
      "numberOfFilesForIndexing" : 0,
      "numberOfFilesFullyIndexedByInfrastructureExtensions" : 0,
      "filesFullyIndexedByInfrastructureExtensions" : [ ],
      "statusTime" : 0,
      "totalOneThreadTimeWithPauses" : 1401430,
      "iterationAndScannersApplicationTime" : 16380,
      "filesCheckTime" : 1329085,
      "timeProcessingUpToDateFiles" : 0,
      "timeUpdatingContentLessIndexes" : 0,
      "timeIndexingWithoutContentViaInfrastructureExtension" : 0,
      "roots" : [ ]
    }, {
      "providerName" : "Indexable set contributor 'Version Catalogs' (non-project)",
      "numberOfScannedFiles" : 0,
      "numberOfSkippedFiles" : 0,
      "numberOfFilesForIndexing" : 0,
      "numberOfFilesFullyIndexedByInfrastructureExtensions" : 0,
      "filesFullyIndexedByInfrastructureExtensions" : [ ],
      "statusTime" : 0,
      "totalOneThreadTimeWithPauses" : 1343533,
      "iterationAndScannersApplicationTime" : 18334,
      "filesCheckTime" : 1292903,
      "timeProcessingUpToDateFiles" : 0,
      "timeUpdatingContentLessIndexes" : 0,
      "timeIndexingWithoutContentViaInfrastructureExtension" : 0,
      "roots" : [ ]
    } ]
  }
}